zeekscript/__init__.py
zeekscript/cli.py
zeekscript/error.py
zeekscript/formatter.py
zeekscript/node.py
zeekscript/output.py
zeekscript/parser.py
zeekscript/script.py
zeekscript/zeek-language.so
zeekscript-1.2.9.data/scripts/zeek-format
zeekscript-1.2.9.data/scripts/zeek-script
zeekscript-1.2.9.dist-info/LICENSE
zeekscript-1.2.9.dist-info/METADATA
zeekscript-1.2.9.dist-info/WHEEL
zeekscript-1.2.9.dist-info/top_level.txt
zeekscript-1.2.9.dist-info/RECORD
