Metadata-Version: 2.1
Name: zeekscript
Version: 1.2.9
Summary: A Zeek script formatter and analyzer
Home-page: https://github.com/zeek/zeekscript
Maintainer: The Zeek Project
Maintainer-email: info@zeek.org
Keywords: zeek scripts language formatter formatting indenter indenting parsing
Classifier: Programming Language :: Python :: 3.7
Classifier: License :: OSI Approved :: BSD License
Classifier: Topic :: Utilities
Requires-Python: >3.8.0
License-File: LICENSE
Requires-Dist: tree-sitter ==0.21.3
